odoo/addons/l10n_ar_invoice_report/README.rst
odoo/addons/l10n_ar_invoice_report/__init__.py
odoo/addons/l10n_ar_invoice_report/__manifest__.py
odoo/addons/l10n_ar_invoice_report/i18n/l10n_ar_invoice_report.pot
odoo/addons/l10n_ar_invoice_report/models/__init__.py
odoo/addons/l10n_ar_invoice_report/models/res_company.py
odoo/addons/l10n_ar_invoice_report/readme/CONTRIBUTORS.rst
odoo/addons/l10n_ar_invoice_report/readme/DESCRIPTION.rst
odoo/addons/l10n_ar_invoice_report/readme/HISTORY.rst
odoo/addons/l10n_ar_invoice_report/readme/ROADMAP.rst
odoo/addons/l10n_ar_invoice_report/readme/USAGE.rst
odoo/addons/l10n_ar_invoice_report/static/icon.png
odoo/addons/l10n_ar_invoice_report/static/description/icon.png
odoo/addons/l10n_ar_invoice_report/static/description/index.html
odoo/addons/l10n_ar_invoice_report/static/images/bank_transfer.png
odoo/addons/l10n_ar_invoice_report/static/images/cheque.png
odoo/addons/l10n_ar_invoice_report/static/images/direct_debit.png
odoo/addons/l10n_ar_invoice_report/static/images/mastercard.png
odoo/addons/l10n_ar_invoice_report/static/images/mercadopago.png
odoo/addons/l10n_ar_invoice_report/static/images/pmc.png
odoo/addons/l10n_ar_invoice_report/static/images/visa.png
odoo/addons/l10n_ar_invoice_report/views/report_invoice_fe_template.xml
odoo/addons/l10n_ar_invoice_report/views/reports.xml
odoo/addons/l10n_ar_invoice_report/views/res_company_views.xml
odoo14_addon_l10n_ar_invoice_report-14.0.1.0.1.dev7.dist-info/METADATA
odoo14_addon_l10n_ar_invoice_report-14.0.1.0.1.dev7.dist-info/WHEEL
odoo14_addon_l10n_ar_invoice_report-14.0.1.0.1.dev7.dist-info/top_level.txt
odoo14_addon_l10n_ar_invoice_report-14.0.1.0.1.dev7.dist-info/RECORD
